vulnissimo/__init__.py
vulnissimo/api.py
vulnissimo/cli.py
vulnissimo/exceptions.py
vulnissimo-0.0.5.dist-info/licenses/LICENSE
vulnissimo-0.0.5.dist-info/METADATA
vulnissimo-0.0.5.dist-info/WHEEL
vulnissimo-0.0.5.dist-info/entry_points.txt
vulnissimo-0.0.5.dist-info/top_level.txt
vulnissimo-0.0.5.dist-info/RECORD
