Metadata-Version: 2.4
Name: vulnissimo
Version: 0.0.5
Summary: Scan web apps from your code.
Author-email: Vulnissimo <contact@vulnissimo.io>
License:                     GNU GENERAL PUBLIC LICENSE
Requires-Python: >=3.9
License-File: LICENSE
Requires-Dist: requests
Requires-Dist: rich
Requires-Dist: typer
Dynamic: license-file
